simpleir/__init__.py
simpleir/configs/__init__.py
simpleir/configs/key_words.py
simpleir/criterion/__init__.py
simpleir/criterion/build.py
simpleir/criterion/mse_loss.py
simpleir/criterion/triplet_margin_loss.py
simpleir/data/__init__.py
simpleir/data/build.py
simpleir/data/dataloader/__init__.py
simpleir/data/dataloader/build.py
simpleir/data/dataset/__init__.py
simpleir/data/dataset/build.py
simpleir/data/dataset/impl/__init__.py
simpleir/data/dataset/impl/cccf.py
simpleir/data/dataset/impl/general_dataset.py
simpleir/data/dataset/impl/image_folder.py
simpleir/data/dataset/impl/oxford.py
simpleir/data/sampler/__init__.py
simpleir/data/sampler/build.py
simpleir/data/sampler/distributed_pk_sampler.py
simpleir/data/sampler/pk_sampler.py
simpleir/engine/__init__.py
simpleir/engine/infer.py
simpleir/models/__init__.py
simpleir/models/build.py
simpleir/models/model_base.py
simpleir/models/impl/__init__.py
simpleir/models/impl/ghostnet.py
simpleir/models/impl/mobilenet.py
simpleir/models/impl/resnet.py
simpleir/models/impl/tiny_autocoder.py
simpleir/utils/__init__.py
simpleir/utils/count.py
simpleir/utils/distance.py
simpleir/utils/norm.py
simpleir/utils/prefetcher.py
simpleir/utils/sort.py
simpleir/utils/util.py
simpleir/utils/extract/__init__.py
simpleir/utils/extract/build.py
simpleir/utils/extract/helper.py
simpleir/utils/extract/impl/__init__.py
simpleir/utils/extract/impl/aggregator.py
simpleir/utils/extract/impl/enhancer.py
simpleir/utils/extract/impl/extractor.py
simpleir/utils/extract/impl/aggregate/__init__.py
simpleir/utils/extract/impl/aggregate/r_mac.py
simpleir/utils/extract/impl/aggregate/spoc.py
simpleir/utils/metric/__init__.py
simpleir/utils/metric/build.py
simpleir/utils/metric/helper.py
simpleir/utils/metric/metric_base.py
simpleir/utils/metric/impl/__init__.py
simpleir/utils/metric/impl/accuracy.py
simpleir/utils/metric/impl/functional.py
simpleir/utils/metric/impl/map.py
simpleir/utils/metric/impl/map_for_oxford.py
simpleir-0.10.0.dist-info/LICENSE
simpleir-0.10.0.dist-info/METADATA
simpleir-0.10.0.dist-info/WHEEL
simpleir-0.10.0.dist-info/top_level.txt
simpleir-0.10.0.dist-info/RECORD
