Metadata-Version: 2.1
Name: simpleir
Version: 0.10.0
Summary: A Simple Framework for Image Retrieval 
Home-page: https://github.com/zjykzj/SimpleIR
Author: zj
Author-email: wy163zhuj@163.com
License: UNKNOWN
Platform: UNKNOWN
Classifier: Programming Language :: Python :: 3
Classifier: Operating System :: OS Independent
Classifier: License :: OSI Approved :: Apache Software License
Requires-Python: >=3.8
License-File: LICENSE
Requires-Dist: Pillow (>=9.0.0)
Requires-Dist: apex (>=0.1)
Requires-Dist: joblib (>=1.1.0)
Requires-Dist: numpy (>=1.22.3)
Requires-Dist: sklearn (>=0.0)
Requires-Dist: torch (>=1.12.0)
Requires-Dist: torchvision (>=0.13.0)
Requires-Dist: tqdm (>=4.63.0)
Requires-Dist: yacs (>=0.1.8)
Requires-Dist: zcls2 (>=0.5.3)
